GenPhylo/__init__.py
GenPhylo/model/__init__.py
GenPhylo/model/math_model.py
GenPhylo/model/matrix_computation.py
GenPhylo/model/model_utils.py
GenPhylo/utils/__init__.py
GenPhylo/utils/alignments_generation.py
GenPhylo/utils/classes.py
GenPhylo/utils/generate_DNA.py
GenPhylo/utils/matrices_generation.py
GenPhylo/utils/misc_utils.py
GenPhylo/utils/save.py
GenPhylo-1.2.1.dist-info/LICENSE.txt
GenPhylo-1.2.1.dist-info/METADATA
GenPhylo-1.2.1.dist-info/WHEEL
GenPhylo-1.2.1.dist-info/top_level.txt
GenPhylo-1.2.1.dist-info/RECORD
