Metadata-Version: 2.1
Name: GenPhylo
Version: 1.2.1
Summary: GenPhylo: An open-source Python module for simulating alignments along phylogenetic trees
Home-page: https://github.com/GenPhyloProject/GenPhylo
Author: Marta Casanellas, Martí Cortada Garcia, Adrià Diéguez Moscardó
Author-email: marta.casanellas@upc.edu
Classifier: Programming Language :: Python :: 3
Classifier: License :: OSI Approved :: GNU General Public License v3 (GPLv3)
Classifier: Operating System :: OS Independent
Requires-Python: >=3.6
License-File: LICENSE.txt
